[
  {
    "id": "basic-fixed-income",
    "title": "Basic: Fixed Income, One Asset",
    "description": "A simple retirement scenario with Social Security starting in year 2 and a single taxable brokerage account used for drawdowns.",
    "data": {
      "plan": { "monthly_expenses": 5000, "duration_months": 360 },
      "income": [
        { "name": "Social Security", "amount": 2200, "start_month": 12, "stop_month": 9999 }
      ],
      "assets": [
        { "name": "Brokerage", "type": "taxable", "balance": 300000, "interest_rate": 0.05, "compounding": "monthly" }
      ]
    }
  },
  {
    "id": "ira-priority",
    "title": "IRA Priority Drawdown",
    "description": "A common case with both a taxable brokerage and a traditional IRA. The drawdown order prioritizes the IRA.",
    "data": {
      "plan": { "monthly_expenses": 6000, "duration_months": 360 },
      "income": [],
      "assets": [
        { "name": "Traditional IRA", "type": "taxable", "balance": 400000, "interest_rate": 0.06, "compounding": "monthly" },
        { "name": "Brokerage", "type": "taxable", "balance": 200000, "interest_rate": 0.04, "compounding": "monthly" }
      ],
      "order": [
        { "account": "Traditional IRA", "order": 1 },
        { "account": "Brokerage", "order": 2 }
      ]
    }
  },
  {
    "id": "phased-work-income",
    "title": "Phased Retirement Work",
    "description": "Retiree works part-time for 2 years post-retirement before fully retiring.",
    "data": {
      "plan": { "monthly_expenses": 5500, "duration_months": 360 },
      "income": [
        { "name": "Part-Time Job", "amount": 2000, "start_month": 0, "stop_month": 24 },
        { "name": "Social Security", "amount": 2500, "start_month": 36 }
      ],
      "assets": [
        { "name": "Brokerage", "type": "taxable", "balance": 250000, "interest_rate": 0.05, "compounding": "monthly" },
        { "name": "Traditional IRA", "type": "taxable", "balance": 300000, "interest_rate": 0.06, "compounding": "monthly" }
      ]
    }
  },
  {
    "id": "inheritance-midstream",
    "title": "Mid-Retirement Inheritance",
    "description": "An inheritance arrives in year 10, boosting available assets and extending sustainability.",
    "data": {
      "plan": { "monthly_expenses": 6000, "duration_months": 360 },
      "income": [
        { "name": "Social Security", "amount": 2400, "start_month": 24 }
      ],
      "assets": [
        { "name": "Brokerage", "type": "taxable", "balance": 200000, "interest_rate": 0.05, "compounding": "monthly" },
        { "name": "Inheritance", "type": "taxable", "balance": 250000, "start_month": 120, "interest_rate": 0.03, "compounding": "monthly" }
      ]
    }
  },
  {
    "id": "emergency-expense",
    "title": "Unexpected Roof Replacement",
    "description": "A major unplanned expense modeled via a negative-balance asset at month 60.",
    "data": {
      "plan": { "monthly_expenses": 5250, "duration_months": 360 },
      "income": [],
      "assets": [
        { "name": "Brokerage", "type": "taxable", "balance": 350000, "interest_rate": 0.05, "compounding": "monthly" },
        { "name": "Roof Replacement", "type": "taxable", "balance": -20000, "start_month": 60 }
      ]
    }
  },
  {
    "id": "dog-acquisition",
    "title": "Getting a Dog in Retirement",
    "description": "Includes a one-time pet setup cost and a monthly expense increase beginning in month 36.",
    "data": {
      "plan": { "monthly_expenses": 5200, "duration_months": 360 },
      "income": [],
      "assets": [
        { "name": "Brokerage", "type": "taxable", "balance": 300000, "interest_rate": 0.04, "compounding": "monthly" },
        { "name": "Dog Setup", "type": "taxable", "balance": -2000, "start_month": 36 }
      ]
    }
  },
  {
    "id": "asset-priority-rotation",
    "title": "Rotating Asset Drawdown Priority",
    "description": "Demonstrates priority-based withdrawals from four types of assets.",
    "data": {
      "plan": { "monthly_expenses": 7000, "duration_months": 360 },
      "income": [],
      "assets": [
        { "name": "Savings", "type": "taxable", "balance": 100000, "interest_rate": 0.02, "compounding": "monthly" },
        { "name": "Brokerage", "type": "taxable", "balance": 200000, "interest_rate": 0.05, "compounding": "monthly" },
        { "name": "Traditional IRA", "type": "taxable", "balance": 400000, "interest_rate": 0.06, "compounding": "monthly" },
        { "name": "Roth IRA", "type": "tax_free", "balance": 50000, "interest_rate": 0.05, "compounding": "monthly" }
      ],
      "order": [
        { "account": "Savings", "order": 1 },
        { "account": "Brokerage", "order": 2 },
        { "account": "Traditional IRA", "order": 3 },
        { "account": "Roth IRA", "order": 4 }
      ]
    }
  },
  {
    "id": "income-gap-early-retirement",
    "title": "Early Retirement With Gap Before Social Security",
    "description": "Retiree stops working at 55 and lives off savings until Social Security starts at 70.",
    "data": {
      "plan": { "monthly_expenses": 6000, "duration_months": 360 },
      "income": [
        { "name": "Social Security", "amount": 3000, "start_month": 180 }
      ],
      "assets": [
        { "name": "Brokerage", "type": "taxable", "balance": 500000, "interest_rate": 0.05, "compounding": "monthly" },
        { "name": "Traditional IRA", "type": "taxable", "balance": 350000, "interest_rate": 0.06, "compounding": "monthly" }
      ],
      "order": [
        { "account": "Brokerage", "order": 1 },
        { "account": "Traditional IRA", "order": 2 }
      ]
    }
  },
  {
    "id": "multiple-windfalls",
    "title": "Multiple Windfalls Throughout Retirement",
    "description": "Demonstrates how different inheritance and sale events affect the projection.",
    "data": {
      "plan": { "monthly_expenses": 6500, "duration_months": 360 },
      "income": [],
      "assets": [
        { "name": "Brokerage", "type": "taxable", "balance": 200000, "interest_rate": 0.04, "compounding": "monthly" },
        { "name": "Inheritance", "type": "taxable", "balance": 150000, "start_month": 72 },
        { "name": "House Sale", "type": "taxable", "balance": 175000, "start_month": 180 }
      ]
    }
  },
  {
    "id": "early-expense-late-income",
    "title": "High Upfront Costs, Delayed Income",
    "description": "Tests sustainability when early expenses hit before income ramps up.",
    "data": {
      "plan": { "monthly_expenses": 7000, "duration_months": 360 },
      "income": [
        { "name": "Pension", "amount": 2500, "start_month": 120 },
        { "name": "Social Security", "amount": 3000, "start_month": 180 }
      ],
      "assets": [
        { "name": "Brokerage", "type": "taxable", "balance": 400000, "interest_rate": 0.05, "compounding": "monthly" },
        { "name": "Traditional IRA", "type": "taxable", "balance": 400000, "interest_rate": 0.06, "compounding": "monthly" },
        { "name": "Car Purchase", "type": "taxable", "balance": -35000, "start_month": 12 }
      ]
    }
  },
  {
    "id": "emergency-fund-first",
    "title": "Draw From Emergency Fund First",
    "description": "Retiree uses emergency fund before touching other assets.",
    "data": {
      "plan": { "monthly_expenses": 5000, "duration_months": 360 },
      "income": [],
      "assets": [
        { "name": "Emergency Fund", "type": "taxable", "balance": 30000, "interest_rate": 0.0 },
        { "name": "Brokerage", "type": "taxable", "balance": 300000, "interest_rate": 0.04, "compounding": "monthly" }
      ],
      "order": [
        { "account": "Emergency Fund", "order": 1 },
        { "account": "Brokerage", "order": 2 }
      ]
    }
  }
]
